virtuaaliviivakoodi/__init__.py
virtuaaliviivakoodi/constants/__init__.py
virtuaaliviivakoodi/constants/symbol_version.py
virtuaaliviivakoodi/constants/virtuaaliviivakoodi_slice.py
virtuaaliviivakoodi/dataclasses/__init__.py
virtuaaliviivakoodi/dataclasses/virtuaaliviivakoodi_deconstruct.py
virtuaaliviivakoodi/deconstructors/__init__.py
virtuaaliviivakoodi/deconstructors/amount.py
virtuaaliviivakoodi/deconstructors/date.py
virtuaaliviivakoodi/deconstructors/iban.py
virtuaaliviivakoodi/deconstructors/reference.py
virtuaaliviivakoodi/exceptions/__init__.py
virtuaaliviivakoodi/normalizers/__init__.py
virtuaaliviivakoodi/normalizers/due_date.py
virtuaaliviivakoodi/normalizers/euro_amount.py
virtuaaliviivakoodi/normalizers/iban.py
virtuaaliviivakoodi/normalizers/reference.py
virtuaaliviivakoodi/utils/__init__.py
virtuaaliviivakoodi/utils/detect_symbol_version.py
virtuaaliviivakoodi/utils/remove_whitespace.py
virtuaaliviivakoodi/utils/split_euros_and_cents.py
virtuaaliviivakoodi/validators/__init__.py
virtuaaliviivakoodi/validators/due_date.py
virtuaaliviivakoodi/validators/euro_amount.py
virtuaaliviivakoodi/validators/iban.py
virtuaaliviivakoodi/validators/length.py
virtuaaliviivakoodi/validators/reference.py
virtuaaliviivakoodi/virtuaaliviivakoodi.py
virtuaaliviivakoodi-1.1.0.dist-info/METADATA
virtuaaliviivakoodi-1.1.0.dist-info/WHEEL
virtuaaliviivakoodi-1.1.0.dist-info/RECORD
