Metadata-Version: 2.1
Name: virtuaaliviivakoodi
Version: 1.1.0
Summary: Python library for generating and reading Finnish virtuaaliviivakoodi's
License: MIT
Author: Juho Enala
Author-email: juho.enala@nocfo.io
Requires-Python: >=3.8
Classifier: License :: OSI Approved :: MIT License
Classifier: Programming Language :: Python :: 3
Classifier: Programming Language :: Python :: 3.8
Classifier: Programming Language :: Python :: 3.9
Classifier: Programming Language :: Python :: 3.10
Classifier: Programming Language :: Python :: 3.11
Classifier: Programming Language :: Python :: 3.12
